{"nodes": [{"id": "d_project_alex_miaosha_mobile_src_views_finance_shopfinance_api_index_ts", "label": "index.ts", "file_type": "code", "source_file": "D:\\project\\alex_miaosha_mobile\\src\\views\\finance\\shopFinance\\api\\index.ts", "source_location": "L1"}, {"id": "index_getshopfinancepage", "label": "getShopFinancePage()", "file_type": "code", "source_file": "D:\\project\\alex_miaosha_mobile\\src\\views\\finance\\shopFinance\\api\\index.ts", "source_location": "L12"}, {"id": "index_getshopfinancedetail", "label": "getShopFinanceDetail()", "file_type": "code", "source_file": "D:\\project\\alex_miaosha_mobile\\src\\views\\finance\\shopFinance\\api\\index.ts", "source_location": "L24"}, {"id": "index_deleteshopfinance", "label": "deleteShopFinance()", "file_type": "code", "source_file": "D:\\project\\alex_miaosha_mobile\\src\\views\\finance\\shopFinance\\api\\index.ts", "source_location": "L28"}, {"id": "index_addshopfinance", "label": "addShopFinance()", "file_type": "code", "source_file": "D:\\project\\alex_miaosha_mobile\\src\\views\\finance\\shopFinance\\api\\index.ts", "source_location": "L32"}, {"id": "index_updateshopfinance", "label": "updateShopFinance()", "file_type": "code", "source_file": "D:\\project\\alex_miaosha_mobile\\src\\views\\finance\\shopFinance\\api\\index.ts", "source_location": "L36"}], "edges": [{"source": "d_project_alex_miaosha_mobile_src_views_finance_shopfinance_api_index_ts", "target": "d_project_alex_miaosha_mobile_src_views_finance_shopfinance_config", "relation": "imports_from", "confidence": "EXTRACTED", "source_file": "D:\\project\\alex_miaosha_mobile\\src\\views\\finance\\shopFinance\\api\\index.ts", "source_location": "L1", "weight": 1.0}, {"source": "d_project_alex_miaosha_mobile_src_views_finance_shopfinance_api_index_ts", "target": "index", "relation": "imports_from", "confidence": "EXTRACTED", "source_file": "D:\\project\\alex_miaosha_mobile\\src\\views\\finance\\shopFinance\\api\\index.ts", "source_location": "L2", "weight": 1.0}, {"source": "d_project_alex_miaosha_mobile_src_views_finance_shopfinance_api_index_ts", "target": "api", "relation": "imports_from", "confidence": "EXTRACTED", "source_file": "D:\\project\\alex_miaosha_mobile\\src\\views\\finance\\shopFinance\\api\\index.ts", "source_location": "L3", "weight": 1.0}, {"source": "d_project_alex_miaosha_mobile_src_views_finance_shopfinance_api_index_ts", "target": "index_getshopfinancepage", "relation": "contains", "confidence": "EXTRACTED", "source_file": "D:\\project\\alex_miaosha_mobile\\src\\views\\finance\\shopFinance\\api\\index.ts", "source_location": "L12", "weight": 1.0}, {"source": "d_project_alex_miaosha_mobile_src_views_finance_shopfinance_api_index_ts", "target": "index_getshopfinancedetail", "relation": "contains", "confidence": "EXTRACTED", "source_file": "D:\\project\\alex_miaosha_mobile\\src\\views\\finance\\shopFinance\\api\\index.ts", "source_location": "L24", "weight": 1.0}, {"source": "d_project_alex_miaosha_mobile_src_views_finance_shopfinance_api_index_ts", "target": "index_deleteshopfinance", "relation": "contains", "confidence": "EXTRACTED", "source_file": "D:\\project\\alex_miaosha_mobile\\src\\views\\finance\\shopFinance\\api\\index.ts", "source_location": "L28", "weight": 1.0}, {"source": "d_project_alex_miaosha_mobile_src_views_finance_shopfinance_api_index_ts", "target": "index_addshopfinance", "relation": "contains", "confidence": "EXTRACTED", "source_file": "D:\\project\\alex_miaosha_mobile\\src\\views\\finance\\shopFinance\\api\\index.ts", "source_location": "L32", "weight": 1.0}, {"source": "d_project_alex_miaosha_mobile_src_views_finance_shopfinance_api_index_ts", "target": "index_updateshopfinance", "relation": "contains", "confidence": "EXTRACTED", "source_file": "D:\\project\\alex_miaosha_mobile\\src\\views\\finance\\shopFinance\\api\\index.ts", "source_location": "L36", "weight": 1.0}], "raw_calls": [{"caller_nid": "index_getshopfinancepage", "callee": "postData", "source_file": "D:\\project\\alex_miaosha_mobile\\src\\views\\finance\\shopFinance\\api\\index.ts", "source_location": "L18"}, {"caller_nid": "index_getshopfinancedetail", "callee": "getData", "source_file": "D:\\project\\alex_miaosha_mobile\\src\\views\\finance\\shopFinance\\api\\index.ts", "source_location": "L25"}, {"caller_nid": "index_deleteshopfinance", "callee": "deleteData", "source_file": "D:\\project\\alex_miaosha_mobile\\src\\views\\finance\\shopFinance\\api\\index.ts", "source_location": "L29"}, {"caller_nid": "index_addshopfinance", "callee": "postData", "source_file": "D:\\project\\alex_miaosha_mobile\\src\\views\\finance\\shopFinance\\api\\index.ts", "source_location": "L33"}, {"caller_nid": "index_updateshopfinance", "callee": "putData", "source_file": "D:\\project\\alex_miaosha_mobile\\src\\views\\finance\\shopFinance\\api\\index.ts", "source_location": "L37"}]}